fastapi_control/__init__.py
fastapi_control/controller.py
fastapi_control/di.py
fastapi_control-0.3.1.dist-info/LICENSE
fastapi_control-0.3.1.dist-info/WHEEL
fastapi_control-0.3.1.dist-info/METADATA
fastapi_control-0.3.1.dist-info/RECORD
