Metadata-Version: 2.1
Name: fastapi-control
Version: 0.3.1
Summary: FastAPI utility to implement class-based routing with controllers and dependency injection.
Home-page: https://github.com/leynier/fastapi-control
License: MIT
Author: Leynier Gutiérrez González
Author-email: leynier41@gmail.com
Requires-Python: >=3.7,<4.0
Classifier: License :: OSI Approved :: MIT License
Classifier: Programming Language :: Python :: 3
Classifier: Programming Language :: Python :: 3.10
Classifier: Programming Language :: Python :: 3.7
Classifier: Programming Language :: Python :: 3.8
Classifier: Programming Language :: Python :: 3.9
Requires-Dist: fastapi (>=0.78.0,<0.79.0)
Requires-Dist: kink (>=0.6.5,<0.7.0)
Project-URL: Documentation, https://github.com/leynier/fastapi-control
Project-URL: Repository, https://github.com/leynier/fastapi-control
